Metadata-Version: 2.1
Name: UIHook
Version: 0.0.1
Summary: UIHook: A versatile toolkit for interacting with and testing various GUI frameworks.
Author-email: James David Clarke <james@jamesdavidclarke.com>
License: Apache-2.0
Project-URL: homepage, https://github.com/JamesClarke7283/UIHook
Project-URL: repository, https://github.com/JamesClarke7283/UIHook
Requires-Python: >=3.8
License-File: LICENSE
Requires-Dist: fastapi
Requires-Dist: requests
Requires-Dist: python-dotenv
Requires-Dist: pydantic
Requires-Dist: customtkinter
Requires-Dist: hypercorn
